fuse/__init__.py
fuse/cells.py
fuse/dof.py
fuse/groups.py
fuse/serialisation.py
fuse/traces.py
fuse/triples.py
fuse/utils.py
fuse/spaces/__init__.py
fuse/spaces/element_sobolev_spaces.py
fuse/spaces/interpolation_spaces.py
fuse/spaces/polynomial_spaces.py
fuse_element-0.1.1.dist-info/LICENSE
fuse_element-0.1.1.dist-info/METADATA
fuse_element-0.1.1.dist-info/WHEEL
fuse_element-0.1.1.dist-info/top_level.txt
fuse_element-0.1.1.dist-info/RECORD
